mecoda_nat/__init__.py
mecoda_nat/mecoda_nat.py
mecoda_nat/models.py
mecoda_nat/py.typed
mecoda_nat/views.py
mecoda_nat-0.6.0.dist-info/LICENSE
mecoda_nat-0.6.0.dist-info/METADATA
mecoda_nat-0.6.0.dist-info/WHEEL
mecoda_nat-0.6.0.dist-info/top_level.txt
mecoda_nat-0.6.0.dist-info/RECORD
