Metadata-Version: 2.1
Name: mecoda-nat
Version: 0.6.0
Summary: Library to download information collected in Natusfera API.
Home-page: https://github.com/pynomaly/mecoda-nat
Author: Ana Alvarez
Author-email: ana.alvarez@icm.csic.es
License: GNU General Public License v3
Platform: UNKNOWN
Classifier: Development Status :: 2 - Pre-Alpha
Classifier: Intended Audience :: Developers
Classifier: License :: OSI Approved :: GNU General Public License v3 or later (GPLv3+)
Classifier: Operating System :: Unix
Classifier: Operating System :: POSIX
Classifier: Programming Language :: Python
Classifier: Programming Language :: Python :: 3
Classifier: Programming Language :: Python :: 3.7
Classifier: Programming Language :: Python :: 3.8
Classifier: Topic :: Utilities
Classifier: Natural Language :: English
Requires-Python: >=3.6
Requires-Dist: flat-table
Requires-Dist: pandas
Requires-Dist: pydantic
Requires-Dist: requests
